p3droslo/__init__.py
p3droslo/forward.py
p3droslo/haar.py
p3droslo/hydrodynamics.py
p3droslo/lines.py
p3droslo/loss.py
p3droslo/model.py
p3droslo/object.py
p3droslo/observation.py
p3droslo/plot.py
p3droslo/reconstruction.py
p3droslo/utils.py
p3droslo-0.0.15.dist-info/LICENSE
p3droslo-0.0.15.dist-info/METADATA
p3droslo-0.0.15.dist-info/WHEEL
p3droslo-0.0.15.dist-info/top_level.txt
p3droslo-0.0.15.dist-info/RECORD
